functions_by_batirova/README.md
functions_by_batirova/math_functions.py
functions_by_batirova-0.2.0.dist-info/WHEEL
functions_by_batirova-0.2.0.dist-info/METADATA
functions_by_batirova-0.2.0.dist-info/RECORD
