Metadata-Version: 2.1
Name: functions-by-batirova
Version: 0.2.0
Summary: This is out test project
Author: Gulnara Batirova
Author-email: batirova@yahoo.com
Requires-Python: >=3.10,<4.0
Classifier: Programming Language :: Python :: 3
Classifier: Programming Language :: Python :: 3.10
Classifier: Programming Language :: Python :: 3.11
